{"primary_count":0,"secondary_count":16,"total_mentions":31,"primary":[],"secondary":[{"path":"T\\T55\\T55n2181.xml","mentions":7,"title":"Annotated Treatises of the Faxiang School","title_zh":"注進法相宗章疏","snippet":"琳 同記一卷 道憲 同抄三卷 同集記三"},{"path":"B\\B17\\B17n0089.xml","mentions":4,"title":"Selections from Taiping Guangji (Volumes 87–134)","title_zh":"太平廣記選輯（卷八十七～一三四）","snippet":"史雋東山沙彌徐善才杜智楷張氏 許儼僧道憲成珪王琦 竺惠慶竺惠慶 宋沙門竺惠慶。廣陵人也。經行修明。元"},{"path":"X\\X78\\X78n1542.xml","mentions":3,"title":"Record of Efficacy from Upholding the Guanyin Sutra","title_zh":"觀音經持驗記","snippet":"唐釋萬迴唐釋僧伽 唐釋慧日唐釋自覺 唐釋道憲唐釋智益 唐中書令岑文本唐徐善才 唐大理丞董雄"},{"path":"T\\T55\\T55n2183.xml","mentions":2,"title":"Catalog of the Transmission of the Lamp in the Eastern Regions","title_zh":"東域傳燈目錄","snippet":"釋玄贊有則 同疏抄五卷道憲金城寺住 同玄贊要集三十五卷鏡水寺栖復撰本末七十卷 同經掌記十卷"},{"path":"J\\J36\\J36nB368.xml","mentions":2,"title":"Recorded Sayings of Chan Master Dulang of Tongxuan Monastery, Tiantai","title_zh":"天台通玄寺獨朗禪師語錄","snippet":"...穎絕良媒。隨時遣興騷莊趣，即景題詩李 杜才，蹤跡繩陽堪彷彿，一回相見一徘徊。 高道憲登太白高道憲登太白 葉落梧桐玉露肥，沖霄靈翮夜知歸，蒼龍秪解傾湫 岳，睡虎何當省..."},{"path":"GA\\GA010\\GA010n0009.xml","mentions":2,"title":"New Gazetteer of Putuo Luojia","title_zh":"普陀洛迦新志","snippet":"...之兇；古廟塵封，託救萬藍之厄。施金反噬，現白衣而解圍；附 載遭沈，引明燈而施救。道憲水中，捧來菩薩；維新足下，托以蓮華。垂失衣鉢，道汪以 雲霧生全；投入蒸籠，元禮得..."},{"path":"B\\B31\\B31n0170.xml","mentions":2,"title":"General History of Korean Buddhism","title_zh":"朝鮮佛教通史","snippet":"...為對。有深旨哉。東還三傳。至大師。畢萬之後斯 驗矣。其世緣則。王都人。金姓子。號道憲。字智詵。父贊瓖。母伊氏。長慶甲辰歲。現于 世。中和壬寅曆。歸于寂。宴坐也四十三..."},{"path":"T\\T52\\T52n2108.xml","mentions":1,"title":"Collected Matters on Why Monastics Should Not Bow to Laypeople, etc.","title_zh":"集沙門不應拜俗等事","snippet":"...緬邈。求之於自形。而上者虔肅拜起 無虧於持戒。若行道不失其為恭王法齊敬 於率土。道憲兼隆內外咸得矣。臣前受外任。 聽承疎短。乃不知去春已有明論。近在直被 詔。便率其..."},{"path":"T\\T52\\T52n2102.xml","mentions":1,"title":"Collection for the Promotion of Brightness","title_zh":"弘明集","snippet":"...邈。求之於自形而上者虔肅拜起。無虧於 持戒。若行道不失其為恭。王法齊敬於率 土。道憲兼隆內外咸得矣。臣前受外任。聽承 疎短。乃不知去春已有明論。近在直被詔。便 率其..."},{"path":"X\\X87\\X87n1622.xml","mentions":1,"title":"Study of Korean Chan and Teachings","title_zh":"朝鮮禪教考","snippet":"...法嗣󳬴在谷城相裏寺。 賢溪智證大師 寂照塔銘云：大師金姓子寂照本智 證之塔，號道憲，字智詵。長慶甲辰現于世，中和壬寅 歸乎寂。發蒙乎梵體大德，亶貝于瓊儀律師，探玄..."},{"path":"GA\\GA021\\GA021n0019.xml","mentions":1,"title":"Gazetteer of Li’an Monastery, Wulin","title_zh":"武林理安寺志","snippet":"...相委。不得 已應請兼攝。三月六日入院，常住荒涼，山場為居人 侵佔，爨薪不給。因訴道憲劉公，諭兩縣追還侵地，寺 遂稍整。越兩月歸理安。會有主理安之席者自京至 杭，遂交..."},{"path":"GA\\GA015\\GA015n0014.xml","mentions":1,"title":"Gazetteer of Yuelin Monastery, Mingzhou","title_zh":"明州岳林寺志","snippet":"... 慈氏亦無可如何耳。康熙初，延自閒禪師株守。踰年，翛 然告退。旋請天伊禪師，白之道憲王公，疏免。幸沿海上 田奉旨遣棄，虛糧盡捐。而天伊適遭奇禍，於是姚江 解齊禪師應..."},{"path":"B\\B33\\B33n0192.xml","mentions":1,"title":"Record of Exegetical Notes (Shiwén Jì)","title_zh":"釋文紀","snippet":"...用耳神理緬邈求 之於自形而上者虔肅拜起無虧於持戒若行道不失 其為恭王法齊敬於率土道憲兼隆內外咸得矣臣前 受外任聽承踈短乃不知去春已有明論近在直被詔 便率其愚情不懼允..."},{"path":"B\\B15\\B15n0088.xml","mentions":1,"title":"Selected Extracts from the Complete Collection of Illustrations and Writings from Antiquity to the Present (Part 1)","title_zh":"古今圖書集成選輯（上）","snippet":"...忙遽誦金 剛經至潀流所忽有一物狀如赤龍橫出扶舟因得 上議者為誦經之功 唐聖善寺僧道憲俗姓元氏開元中住持於江州大 雲寺法侶稱之時刺史元某欲畫觀世音七鋪以憲 練行委之勾..."},{"path":"B\\B13\\B13n0079.xml","mentions":1,"title":"Six Tablets of the Śākya Clan (Buddhist Encyclopedia)","title_zh":"釋氏六帖","snippet":"...之用耳神理緬懇求之於自形而上者虔肅拜起無虧於持戒若 行道不失其為恭王法齊敬於率土道憲兼隆內外咸得矣臣前受外王聽承疏短乃不知去春已有明論近在直被詔便率其愚情不懼允洽還..."},{"path":"T\\T52\\T52n2120.xml","mentions":1,"title":"Collected Memorials and Edicts for the Tripitaka Preceptor, Posthumously Honored as Sikong, Great Defender of the Correct and Broad Wisdom, in Daizong’s Reign","title_zh":"代宗朝贈司空大辨正廣智三藏和上表制集","snippet":"...太原府至德寺。置一文殊師利菩薩 院。并抽三學大德二七人。遞弘本教以續法 燈。仍請道憲法師於此寺長時講說者。宜依 牒。至准 勅故牒。 大曆五年七月十三日牒 中書侍郎平..."}]}