{"primary_count":0,"secondary_count":10,"total_mentions":18,"primary":[],"secondary":[{"path":"X\\X84\\X84n1579.xml","mentions":3,"title":"Continuation of the Record Pointing at the Moon","title_zh":"續指月錄","snippet":"...嗣 襄陽大覺圓禪師天池素嗣 嘉興無趣如空禪師野翁曉嗣 大休宗隆禪師無盡海嗣 嘉興雲谷法會禪師 嘉興東谿澤禪師已上二人天寧濟嗣 浮峰普恩上座"},{"path":"X\\X67\\X67n1308.xml","mentions":2,"title":"Path-Stone: Dripping Milk Collection","title_zh":"徑石滴乳集","snippet":"法嗣 南宗法印禪師 西林頂禪師法嗣 能仁濟舟法洪禪師 天寧濟禪師法嗣 胥山雲谷法會禪師 精嚴冬溪方澤禪師 天池聚禪師法嗣 浮峰普恩上座語別見 薦福愷禪師法嗣"},{"path":"X\\X84\\X84n1585.xml","mentions":2,"title":"Drafts for the Continuation of the Lamp","title_zh":"續燈存稿","snippet":"茄子。 天寧濟禪師法嗣天寧濟禪師法嗣 嘉興府胥山雲谷法會禪師嘉興府胥山雲谷法會禪師本郡嘉善懷氏子。芟染 於大雲寺。時法舟掩室於天寧，師往..."},{"path":"X\\X84\\X84n1583.xml","mentions":2,"title":"Orthodox Continuation of the Lamp","title_zh":"續燈正統","snippet":"僧臘五十三。 天寧濟禪師法嗣天寧濟禪師法嗣 嘉興府胥山雲谷法會禪師嘉興府胥山雲谷法會禪師嘉善懷氏子。投大雲寺 芟染。時法舟掩室天寧，師往參，舟..."},{"path":"X\\X82\\X82n1571.xml","mentions":2,"title":"Complete Five Lamps (Vols. 34–120)","title_zh":"五燈全書(第34卷-第120卷)","snippet":"端坐而逝。 天寧濟禪師法嗣天寧濟禪師法嗣 嘉興府胥山雲谷法會禪師嘉興府胥山雲谷法會禪師本郡嘉善懷氏子。芟染 於大雲寺。時法舟掩室於天寧，師往..."},{"path":"X\\X81\\X81n1568.xml","mentions":2,"title":"Strict Lineage of the Five Lamps (Vols. 10–25)","title_zh":"五燈嚴統(第10卷-第25卷)","snippet":"十三，坐五十三夏。 天寧濟禪師法嗣天寧濟禪師法嗣 嘉興府胥山雲谷法會禪師嘉興府胥山雲谷法會禪師嘉善懷氏子。參法舟於 天寧，舟令參念佛是誰話。一日受食..."},{"path":"X\\X80\\X80n1566.xml","mentions":2,"title":"Five Lamps Compendium: Continued Abridgment","title_zh":"五燈會元續略","snippet":"偈，是從上果地人之語也。 天寧濟禪師法嗣天寧濟禪師法嗣 嘉興府胥山雲谷法會禪師嘉興府胥山雲谷法會禪師郡之嘉善懷氏子。依大 雲寺出家。時法舟掩關天寧，師往參..."},{"path":"X\\X77\\X77n1524.xml","mentions":1,"title":"Supplement to the Continued Biographies of Eminent Monks","title_zh":"補續高僧傳","snippet":"...道成禪師 古淵清禪師 觀音真空禪師 古峰繼萬闍梨 張家橋滿賢禪師 無明慧經禪師 雲谷法會禪師 卷第十七 明律篇第四 宋柳律師圓覺律師 了興禪師 遼法均傳戒大師附裕窺 金..."},{"path":"X\\X86\\X86n1600.xml","mentions":1,"title":"Chronological Compilation of the Sectarian Lineage","title_zh":"宗統編年","snippet":"十月七日，生於常州無錫蘇氏。 甲戌二年 禪師天甯下大雲，雲谷法會寂。 會，嘉善懷氏子。參法舟濟於天甯，寢食俱廢。一日 食盡，不知碗忽墮地，𨺗然..."},{"path":"X\\X81\\X81n1570.xml","mentions":1,"title":"Table of Contents of the Complete Five Lamps","title_zh":"五燈全書目錄","snippet":"無趣如空禪師 無盡海禪師法嗣 七尖大休宗隆禪師 天寧濟禪師法嗣 胥山雲谷法會禪師 精巖東谿方澤禪師 天池聚禪師法嗣 浮峯普恩上座 斗峰琴禪師法嗣 斗峰天真道..."}]}